py_dictfind/__init__.py
py_dictfind/exceptions.py
py_dictfind/logs.py
py_dictfind/models/__init__.py
py_dictfind/models/checker.py
py_dictfind/models/grammar.py
py_dictfind/models/visitor.py
py_dictfind/operations/__init__.py
py_dictfind/operations/check.py
py_dictfind/operations/find.py
py_dictfind-0.1.1.dist-info/METADATA
py_dictfind-0.1.1.dist-info/WHEEL
py_dictfind-0.1.1.dist-info/licenses/LICENSE
py_dictfind-0.1.1.dist-info/RECORD
